modeltranslation_wagtail/__init__.py
modeltranslation_wagtail/apps.py
modeltranslation_wagtail/translator.py
django_modeltranslation_wagtail-0.4.1.dist-info/LICENSE
django_modeltranslation_wagtail-0.4.1.dist-info/METADATA
django_modeltranslation_wagtail-0.4.1.dist-info/WHEEL
django_modeltranslation_wagtail-0.4.1.dist-info/top_level.txt
django_modeltranslation_wagtail-0.4.1.dist-info/RECORD
