Metadata-Version: 2.1
Name: django-modeltranslation-wagtail
Version: 0.4.1
Summary: The glue between django-modeltranslation and wagtail
Home-page: https://github.com/benjaoming/django-modeltranslation-wagtail
Author: Benjamin Bach
Author-email: benjamin@overtag.dk
License: MIT
Keywords: modeltranslation_wagtail
Platform: UNKNOWN
Classifier: Development Status :: 2 - Pre-Alpha
Classifier: Intended Audience :: Developers
Classifier: License :: OSI Approved :: MIT License
Classifier: Natural Language :: English
Classifier: Programming Language :: Python :: 3
Classifier: Programming Language :: Python :: Implementation :: PyPy
Classifier: Framework :: Django
Classifier: Topic :: Software Development :: Internationalization
License-File: LICENSE
Requires-Dist: wagtail (>=2.0)
Requires-Dist: django-modeltranslation (>=0.12)
